onlymaze/__init__.py
onlymaze/maze.py
onlymaze-1.0.6.dist-info/METADATA
onlymaze-1.0.6.dist-info/WHEEL
onlymaze-1.0.6.dist-info/entry_points.txt
onlymaze-1.0.6.dist-info/top_level.txt
onlymaze-1.0.6.dist-info/RECORD
