Metadata-Version: 2.1
Name: onlymaze
Version: 1.0.6
Summary: A simple maze game.
Home-page: UNKNOWN
License: UNKNOWN
Platform: UNKNOWN
Requires-Dist: tk
